payment_provider/__init__.py
payment_provider/api.py
payment_provider/checkout.py
payment_provider/configuration.py
payment_provider/exceptions.py
payment_provider/helpers.py
payment_provider/order.py
payment_provider/payment.py
payment_provider/resources.py
payment_provider/utils.py
payment_provider-1.0.0.dist-info/LICENSE
payment_provider-1.0.0.dist-info/METADATA
payment_provider-1.0.0.dist-info/WHEEL
payment_provider-1.0.0.dist-info/top_level.txt
payment_provider-1.0.0.dist-info/RECORD
